fastvideo_kernel/__init__.py
fastvideo_kernel/ops.py
fastvideo_kernel/turbodiffusion_ops.py
fastvideo_kernel/version.py
fastvideo_kernel/vmoba.py
fastvideo_kernel/_C/fastvideo_kernel_ops.cpython-312-x86_64-linux-gnu.so
fastvideo_kernel/triton_kernels/block_sparse_attn_triton.py
fastvideo_kernel/triton_kernels/index.py
fastvideo_kernel/triton_kernels/sla_triton.py
fastvideo_kernel/triton_kernels/st_attn_triton.py
fastvideo_kernel-0.2.2.dist-info/METADATA
fastvideo_kernel-0.2.2.dist-info/WHEEL
fastvideo_kernel-0.2.2.dist-info/RECORD
fastvideo_kernel-0.2.2.dist-info/licenses/LICENSE
