Metadata-Version: 2.1
Name: fastvideo-kernel
Version: 0.2.2
Summary: Unified CUDA kernels for FastVideo
Author-Email: Hao AI Lab <contact@haoailab.com>
License:                                  Apache License
Classifier: Programming Language :: Python :: 3
Classifier: Environment :: GPU :: NVIDIA CUDA
Project-URL: Homepage, https://github.com/hao-ai-lab/FastVideo
Requires-Python: >=3.10
Requires-Dist: torch>=2.5.0
Requires-Dist: triton>=2.0.0
